tensortrap/__init__.py
tensortrap/__main__.py
tensortrap/cli.py
tensortrap/formats/__init__.py
tensortrap/formats/gguf_parser.py
tensortrap/formats/magic.py
tensortrap/formats/onnx_parser.py
tensortrap/formats/pickle_parser.py
tensortrap/formats/pytorch_zip.py
tensortrap/formats/safetensors_parser.py
tensortrap/output/__init__.py
tensortrap/output/console.py
tensortrap/output/json_output.py
tensortrap/output/reports.py
tensortrap/scanner/__init__.py
tensortrap/scanner/comfyui_scanner.py
tensortrap/scanner/context_analyzer.py
tensortrap/scanner/engine.py
tensortrap/scanner/external_validators.py
tensortrap/scanner/gguf_scanner.py
tensortrap/scanner/keras_scanner.py
tensortrap/scanner/obfuscation.py
tensortrap/scanner/onnx_scanner.py
tensortrap/scanner/pickle_scanner.py
tensortrap/scanner/polyglot_scanner.py
tensortrap/scanner/recommendations.py
tensortrap/scanner/results.py
tensortrap/scanner/safetensors_scanner.py
tensortrap/scanner/yaml_scanner.py
tensortrap/signatures/__init__.py
tensortrap/signatures/dangerous_imports.py
tensortrap/signatures/patterns.py
tensortrap-1.0.0.dist-info/METADATA
tensortrap-1.0.0.dist-info/WHEEL
tensortrap-1.0.0.dist-info/entry_points.txt
tensortrap-1.0.0.dist-info/licenses/LICENSE
tensortrap-1.0.0.dist-info/RECORD
