Metadata-Version: 2.4
Name: tensortrap
Version: 1.0.0
Summary: Security scanner for AI/ML model files
Project-URL: Homepage, https://github.com/realmarauder/TensorTrap
Project-URL: Documentation, https://github.com/realmarauder/TensorTrap#readme
Project-URL: Repository, https://github.com/realmarauder/TensorTrap
Project-URL: Issues, https://github.com/realmarauder/TensorTrap/issues
Project-URL: Changelog, https://github.com/realmarauder/TensorTrap/blob/main/CHANGELOG.md
Author-email: realmarauder <smichael.us@gmail.com>
License: MIT
License-File: LICENSE
Keywords: ai,civitai,comfyui,gguf,huggingface,machine-learning,malware,ml,pickle,safetensors,scanner,security,swarmui
Classifier: Development Status :: 5 - Production/Stable
Classifier: Environment :: Console
Classifier: Intended Audience :: Developers
Classifier: Intended Audience :: Science/Research
Classifier: License :: OSI Approved :: MIT License
Classifier: Operating System :: OS Independent
Classifier: Programming Language :: Python :: 3
Classifier: Programming Language :: Python :: 3.10
Classifier: Programming Language :: Python :: 3.11
Classifier: Programming Language :: Python :: 3.12
Classifier: Topic :: Scientific/Engineering :: Artificial Intelligence
Classifier: Topic :: Security
Requires-Python: >=3.10
Requires-Dist: rich>=13.0.0
Requires-Dist: safetensors>=0.4.0
Requires-Dist: typer>=0.9.0
Provides-Extra: dev
Requires-Dist: black>=23.0.0; extra == 'dev'
Requires-Dist: mypy>=1.0.0; extra == 'dev'
Requires-Dist: pytest-cov>=4.0.0; extra == 'dev'
Requires-Dist: pytest>=7.0.0; extra == 'dev'
Requires-Dist: ruff>=0.1.0; extra == 'dev'
